lemaster.py
lemaster-0.1.5.dist-info/DESCRIPTION.rst
lemaster-0.1.5.dist-info/METADATA
lemaster-0.1.5.dist-info/RECORD
lemaster-0.1.5.dist-info/WHEEL
lemaster-0.1.5.dist-info/entry_points.txt
lemaster-0.1.5.dist-info/metadata.json
lemaster-0.1.5.dist-info/top_level.txt
