Metadata-Version: 2.0
Name: lemaster
Version: 0.1.5
Summary: Master plugin for the Le bot.
Home-page: https://github.com/cganterh/lemaster
Author: Cristóbal Ganter
Author-email: cganterh@gmail.com
License: MIT
Keywords: python,python3,telegram-bot,chatbot
Platform: UNKNOWN
Classifier: Development Status :: 3 - Alpha
Classifier: Environment :: Web Environment
Classifier: Intended Audience :: System Administrators
Classifier: License :: OSI Approved :: MIT License
Classifier: Natural Language :: English
Classifier: Programming Language :: Python :: 3.5
Classifier: Programming Language :: Python :: 3.6
Classifier: Topic :: Communications :: Chat
Requires-Python: ~=3.5
Requires-Dist: python-telegram-bot (~=10.0)
